{
  "Fairfield": {
    "dateStr": "9/13/20",
    "cases": 19360,
    "deaths": 1418,
    "recovered": 0,
    "new": 0,
    "newDeaths": 0
  },
  "Hartford": {
    "dateStr": "9/13/20",
    "cases": 13886,
    "deaths": 1430,
    "recovered": 0,
    "new": 0,
    "newDeaths": 0
  },
  "Litchfield": {
    "dateStr": "9/13/20",
    "cases": 1773,
    "deaths": 139,
    "recovered": 0,
    "new": 0,
    "newDeaths": 0
  },
  "Middlesex": {
    "dateStr": "9/13/20",
    "cases": 1512,
    "deaths": 193,
    "recovered": 0,
    "new": 0,
    "newDeaths": 0
  },
  "New Haven": {
    "dateStr": "9/13/20",
    "cases": 13961,
    "deaths": 1111,
    "recovered": 0,
    "new": 0,
    "newDeaths": 0
  },
  "New London": {
    "dateStr": "9/13/20",
    "cases": 1651,
    "deaths": 110,
    "recovered": 0,
    "new": 0,
    "newDeaths": 0
  },
  "Out of CT": {
    "dateStr": "9/13/20",
    "cases": 0,
    "deaths": 0,
    "recovered": 0,
    "new": 0,
    "newDeaths": 0
  },
  "Tolland": {
    "dateStr": "9/13/20",
    "cases": 1232,
    "deaths": 66,
    "recovered": 0,
    "new": 0,
    "newDeaths": 0
  },
  "Unassigned": {
    "dateStr": "9/13/20",
    "cases": 550,
    "deaths": 52,
    "recovered": 0,
    "new": 0,
    "newDeaths": 0
  },
  "Windham": {
    "dateStr": "9/13/20",
    "cases": 844,
    "deaths": 15,
    "recovered": 0,
    "new": 0,
    "newDeaths": 0
  }
}