{
  "Fairfield": {
    "dateStr": "9/4/20",
    "cases": 19031,
    "deaths": 1415,
    "recovered": 0,
    "new": 36,
    "newDeaths": 0
  },
  "Hartford": {
    "dateStr": "9/4/20",
    "cases": 13635,
    "deaths": 1426,
    "recovered": 0,
    "new": 37,
    "newDeaths": 0
  },
  "Litchfield": {
    "dateStr": "9/4/20",
    "cases": 1728,
    "deaths": 139,
    "recovered": 0,
    "new": 7,
    "newDeaths": 0
  },
  "Middlesex": {
    "dateStr": "9/4/20",
    "cases": 1484,
    "deaths": 192,
    "recovered": 0,
    "new": 15,
    "newDeaths": 0
  },
  "New Haven": {
    "dateStr": "9/4/20",
    "cases": 13793,
    "deaths": 1111,
    "recovered": 0,
    "new": 30,
    "newDeaths": 0
  },
  "New London": {
    "dateStr": "9/4/20",
    "cases": 1620,
    "deaths": 107,
    "recovered": 0,
    "new": 22,
    "newDeaths": 0
  },
  "Out of CT": {
    "dateStr": "9/4/20",
    "cases": 0,
    "deaths": 0,
    "recovered": 0,
    "new": 0,
    "newDeaths": 0
  },
  "Tolland": {
    "dateStr": "9/4/20",
    "cases": 1161,
    "deaths": 66,
    "recovered": 0,
    "new": 3,
    "newDeaths": 0
  },
  "Unassigned": {
    "dateStr": "9/4/20",
    "cases": 550,
    "deaths": 52,
    "recovered": 0,
    "new": 0,
    "newDeaths": 0
  },
  "Windham": {
    "dateStr": "9/4/20",
    "cases": 813,
    "deaths": 15,
    "recovered": 0,
    "new": 3,
    "newDeaths": 0
  }
}