{
  "Hawaii": {
    "dateStr": "11/4/20",
    "cases": 1332,
    "deaths": 31,
    "recovered": 0,
    "new": 21,
    "newDeaths": 0
  },
  "Honolulu": {
    "dateStr": "11/4/20",
    "cases": 13445,
    "deaths": 170,
    "recovered": 0,
    "new": 124,
    "newDeaths": 0
  },
  "Kalawao": {
    "dateStr": "11/4/20",
    "cases": 0,
    "deaths": 0,
    "recovered": 0,
    "new": 0,
    "newDeaths": 0
  },
  "Kauai": {
    "dateStr": "11/4/20",
    "cases": 67,
    "deaths": 0,
    "recovered": 0,
    "new": 0,
    "newDeaths": 0
  },
  "Maui": {
    "dateStr": "11/4/20",
    "cases": 535,
    "deaths": 18,
    "recovered": 0,
    "new": 5,
    "newDeaths": 0
  },
  "Out of HI": {
    "dateStr": "11/4/20",
    "cases": 94,
    "deaths": 1,
    "recovered": 0,
    "new": 5,
    "newDeaths": 0
  },
  "Unassigned": {
    "dateStr": "11/4/20",
    "cases": 21,
    "deaths": 1,
    "recovered": 0,
    "new": 0,
    "newDeaths": 0
  }
}