{
  "Afghanistan": {
    "dateStr": "12/26/20",
    "cases": 50886,
    "deaths": 2149,
    "recovered": 40784,
    "new": 76,
    "newDeaths": 10
  },
  "Albania": {
    "dateStr": "12/26/20",
    "cases": 55755,
    "deaths": 1143,
    "recovered": 31181,
    "new": 375,
    "newDeaths": 9
  },
  "Algeria": {
    "dateStr": "12/26/20",
    "cases": 97857,
    "deaths": 2722,
    "recovered": 65505,
    "new": 416,
    "newDeaths": 6
  },
  "Andorra": {
    "dateStr": "12/26/20",
    "cases": 7806,
    "deaths": 83,
    "recovered": 7252,
    "new": 50,
    "newDeaths": 0
  },
  "Angola": {
    "dateStr": "12/26/20",
    "cases": 17149,
    "deaths": 399,
    "recovered": 9976,
    "new": 50,
    "newDeaths": 3
  },
  "Antigua and Barbuda": {
    "dateStr": "12/26/20",
    "cases": 155,
    "deaths": 5,
    "recovered": 146,
    "new": 0,
    "newDeaths": 0
  },
  "Argentina": {
    "dateStr": "12/26/20",
    "cases": 1578267,
    "deaths": 42501,
    "recovered": 1402227,
    "new": 3713,
    "newDeaths": 79
  },
  "Armenia": {
    "dateStr": "12/26/20",
    "cases": 157349,
    "deaths": 2752,
    "recovered": 138669,
    "new": 586,
    "newDeaths": 19
  },
  "Austria": {
    "dateStr": "12/26/20",
    "cases": 350484,
    "deaths": 5843,
    "recovered": 320753,
    "new": 1429,
    "newDeaths": 60
  },
  "Azerbaijan": {
    "dateStr": "12/26/20",
    "cases": 213192,
    "deaths": 2454,
    "recovered": 164500,
    "new": 1428,
    "newDeaths": 38
  },
  "Bahamas": {
    "dateStr": "12/26/20",
    "cases": 7788,
    "deaths": 169,
    "recovered": 6166,
    "new": 0,
    "newDeaths": 0
  },
  "Bahrain": {
    "dateStr": "12/26/20",
    "cases": 91518,
    "deaths": 351,
    "recovered": 89326,
    "new": 214,
    "newDeaths": 0
  },
  "Bangladesh": {
    "dateStr": "12/26/20",
    "cases": 508099,
    "deaths": 7428,
    "recovered": 450488,
    "new": 834,
    "newDeaths": 30
  },
  "Barbados": {
    "dateStr": "12/26/20",
    "cases": 352,
    "deaths": 7,
    "recovered": 296,
    "new": 5,
    "newDeaths": 0
  },
  "Belarus": {
    "dateStr": "12/26/20",
    "cases": 184922,
    "deaths": 1376,
    "recovered": 164538,
    "new": 1916,
    "newDeaths": 9
  },
  "Belgium": {
    "dateStr": "12/26/20",
    "cases": 638030,
    "deaths": 19158,
    "recovered": 31130,
    "new": 784,
    "newDeaths": 69
  },
  "Belize": {
    "dateStr": "12/26/20",
    "cases": 10490,
    "deaths": 228,
    "recovered": 9081,
    "new": 0,
    "newDeaths": 0
  },
  "Benin": {
    "dateStr": "12/26/20",
    "cases": 3205,
    "deaths": 44,
    "recovered": 3061,
    "new": 0,
    "newDeaths": 0
  },
  "Bhutan": {
    "dateStr": "12/26/20",
    "cases": 597,
    "deaths": 0,
    "recovered": 445,
    "new": 21,
    "newDeaths": 0
  },
  "Bolivia": {
    "dateStr": "12/26/20",
    "cases": 154349,
    "deaths": 9093,
    "recovered": 129969,
    "new": 759,
    "newDeaths": 10
  },
  "Bosnia and Herzegovina": {
    "dateStr": "12/26/20",
    "cases": 109330,
    "deaths": 3923,
    "recovered": 75124,
    "new": 439,
    "newDeaths": 22
  },
  "Botswana": {
    "dateStr": "12/26/20",
    "cases": 14025,
    "deaths": 40,
    "recovered": 11627,
    "new": 0,
    "newDeaths": 0
  },
  "Brazil": {
    "dateStr": "12/26/20",
    "cases": 7465806,
    "deaths": 190795,
    "recovered": 6654189,
    "new": 17246,
    "newDeaths": 307
  },
  "Brunei": {
    "dateStr": "12/26/20",
    "cases": 152,
    "deaths": 3,
    "recovered": 149,
    "new": 0,
    "newDeaths": 0
  },
  "Bulgaria": {
    "dateStr": "12/26/20",
    "cases": 197384,
    "deaths": 7123,
    "recovered": 109742,
    "new": 469,
    "newDeaths": 50
  },
  "Burkina Faso": {
    "dateStr": "12/26/20",
    "cases": 6255,
    "deaths": 77,
    "recovered": 4588,
    "new": 121,
    "newDeaths": 0
  },
  "Burma": {
    "dateStr": "12/26/20",
    "cases": 121280,
    "deaths": 2579,
    "recovered": 102163,
    "new": 734,
    "newDeaths": 27
  },
  "Burundi": {
    "dateStr": "12/26/20",
    "cases": 786,
    "deaths": 2,
    "recovered": 687,
    "new": 0,
    "newDeaths": 0
  },
  "Cabo Verde": {
    "dateStr": "12/26/20",
    "cases": 11698,
    "deaths": 112,
    "recovered": 11426,
    "new": 2,
    "newDeaths": 0
  },
  "Cambodia": {
    "dateStr": "12/26/20",
    "cases": 364,
    "deaths": 0,
    "recovered": 356,
    "new": 1,
    "newDeaths": 0
  },
  "Cameroon": {
    "dateStr": "12/26/20",
    "cases": 26277,
    "deaths": 448,
    "recovered": 24892,
    "new": 0,
    "newDeaths": 0
  },
  "Central African Republic": {
    "dateStr": "12/26/20",
    "cases": 4948,
    "deaths": 63,
    "recovered": 1924,
    "new": 0,
    "newDeaths": 0
  },
  "Chad": {
    "dateStr": "12/26/20",
    "cases": 1986,
    "deaths": 103,
    "recovered": 1654,
    "new": 15,
    "newDeaths": 1
  },
  "Chile": {
    "dateStr": "12/26/20",
    "cases": 598394,
    "deaths": 16404,
    "recovered": 567376,
    "new": 2563,
    "newDeaths": 46
  },
  "Colombia": {
    "dateStr": "12/26/20",
    "cases": 1584903,
    "deaths": 41943,
    "recovered": 1444041,
    "new": 10196,
    "newDeaths": 253
  },
  "Comoros": {
    "dateStr": "12/26/20",
    "cases": 715,
    "deaths": 7,
    "recovered": 626,
    "new": 0,
    "newDeaths": 0
  },
  "Congo (Brazzaville)": {
    "dateStr": "12/26/20",
    "cases": 6908,
    "deaths": 114,
    "recovered": 5831,
    "new": 337,
    "newDeaths": 0
  },
  "Congo (Kinshasa)": {
    "dateStr": "12/26/20",
    "cases": 16763,
    "deaths": 573,
    "recovered": 13982,
    "new": 291,
    "newDeaths": 0
  },
  "Costa Rica": {
    "dateStr": "12/26/20",
    "cases": 162990,
    "deaths": 2086,
    "recovered": 128842,
    "new": 0,
    "newDeaths": 0
  },
  "Cote d'Ivoire": {
    "dateStr": "12/26/20",
    "cases": 22081,
    "deaths": 133,
    "recovered": 21697,
    "new": 0,
    "newDeaths": 0
  },
  "Croatia": {
    "dateStr": "12/26/20",
    "cases": 204312,
    "deaths": 3613,
    "recovered": 189055,
    "new": 350,
    "newDeaths": 65
  },
  "Cuba": {
    "dateStr": "12/26/20",
    "cases": 11038,
    "deaths": 141,
    "recovered": 9599,
    "new": 138,
    "newDeaths": 1
  },
  "Cyprus": {
    "dateStr": "12/26/20",
    "cases": 19391,
    "deaths": 111,
    "recovered": 2057,
    "new": 25,
    "newDeaths": 2
  },
  "Czechia": {
    "dateStr": "12/26/20",
    "cases": 667569,
    "deaths": 10950,
    "recovered": 563454,
    "new": 2706,
    "newDeaths": 91
  },
  "Denmark": {
    "dateStr": "12/26/20",
    "cases": 151167,
    "deaths": 1153,
    "recovered": 108659,
    "new": 1834,
    "newDeaths": 19
  },
  "Diamond Princess": {
    "dateStr": "12/26/20",
    "cases": 712,
    "deaths": 13,
    "recovered": 699,
    "new": 0,
    "newDeaths": 0
  },
  "Djibouti": {
    "dateStr": "12/26/20",
    "cases": 5805,
    "deaths": 61,
    "recovered": 5699,
    "new": 1,
    "newDeaths": 0
  },
  "Dominica": {
    "dateStr": "12/26/20",
    "cases": 88,
    "deaths": 0,
    "recovered": 83,
    "new": 0,
    "newDeaths": 0
  },
  "Dominican Republic": {
    "dateStr": "12/26/20",
    "cases": 165940,
    "deaths": 2404,
    "recovered": 127866,
    "new": 905,
    "newDeaths": 0
  },
  "Ecuador": {
    "dateStr": "12/26/20",
    "cases": 209274,
    "deaths": 13990,
    "recovered": 181618,
    "new": 446,
    "newDeaths": 6
  },
  "Egypt": {
    "dateStr": "12/26/20",
    "cases": 131315,
    "deaths": 7352,
    "recovered": 109462,
    "new": 1189,
    "newDeaths": 43
  },
  "El Salvador": {
    "dateStr": "12/26/20",
    "cases": 44619,
    "deaths": 1297,
    "recovered": 39989,
    "new": 0,
    "newDeaths": 8
  },
  "Equatorial Guinea": {
    "dateStr": "12/26/20",
    "cases": 5236,
    "deaths": 85,
    "recovered": 5078,
    "new": 0,
    "newDeaths": 0
  },
  "Eritrea": {
    "dateStr": "12/26/20",
    "cases": 992,
    "deaths": 1,
    "recovered": 600,
    "new": 0,
    "newDeaths": 0
  },
  "Estonia": {
    "dateStr": "12/26/20",
    "cases": 25027,
    "deaths": 204,
    "recovered": 15688,
    "new": 445,
    "newDeaths": 2
  },
  "Eswatini": {
    "dateStr": "12/26/20",
    "cases": 8367,
    "deaths": 163,
    "recovered": 7016,
    "new": 197,
    "newDeaths": 9
  },
  "Ethiopia": {
    "dateStr": "12/26/20",
    "cases": 122413,
    "deaths": 1901,
    "recovered": 108269,
    "new": 533,
    "newDeaths": 4
  },
  "Fiji": {
    "dateStr": "12/26/20",
    "cases": 46,
    "deaths": 2,
    "recovered": 44,
    "new": 0,
    "newDeaths": 0
  },
  "Finland": {
    "dateStr": "12/26/20",
    "cases": 34821,
    "deaths": 524,
    "recovered": 26000,
    "new": 173,
    "newDeaths": 0
  },
  "France": {
    "dateStr": "12/26/20",
    "cases": 2548388,
    "deaths": 62209,
    "recovered": 165923,
    "new": 3030,
    "newDeaths": 146
  },
  "Gabon": {
    "dateStr": "12/26/20",
    "cases": 9497,
    "deaths": 64,
    "recovered": 9331,
    "new": 0,
    "newDeaths": 0
  },
  "Gambia": {
    "dateStr": "12/26/20",
    "cases": 3791,
    "deaths": 123,
    "recovered": 3659,
    "new": 0,
    "newDeaths": 0
  },
  "Georgia": {
    "dateStr": "12/26/20",
    "cases": 220508,
    "deaths": 2352,
    "recovered": 200339,
    "new": 1784,
    "newDeaths": 39
  },
  "Germany": {
    "dateStr": "12/26/20",
    "cases": 1646240,
    "deaths": 29946,
    "recovered": 1253285,
    "new": 13504,
    "newDeaths": 366
  },
  "Ghana": {
    "dateStr": "12/26/20",
    "cases": 54286,
    "deaths": 333,
    "recovered": 53082,
    "new": 243,
    "newDeaths": 0
  },
  "Greece": {
    "dateStr": "12/26/20",
    "cases": 135114,
    "deaths": 4553,
    "recovered": 93764,
    "new": 262,
    "newDeaths": 46
  },
  "Grenada": {
    "dateStr": "12/26/20",
    "cases": 112,
    "deaths": 0,
    "recovered": 57,
    "new": 0,
    "newDeaths": 0
  },
  "Guatemala": {
    "dateStr": "12/26/20",
    "cases": 135171,
    "deaths": 4763,
    "recovered": 123893,
    "new": 91,
    "newDeaths": 6
  },
  "Guinea": {
    "dateStr": "12/26/20",
    "cases": 13646,
    "deaths": 80,
    "recovered": 13049,
    "new": 0,
    "newDeaths": 0
  },
  "Guinea-Bissau": {
    "dateStr": "12/26/20",
    "cases": 2447,
    "deaths": 45,
    "recovered": 2386,
    "new": 0,
    "newDeaths": 0
  },
  "Guyana": {
    "dateStr": "12/26/20",
    "cases": 6289,
    "deaths": 162,
    "recovered": 5652,
    "new": 0,
    "newDeaths": 0
  },
  "Haiti": {
    "dateStr": "12/26/20",
    "cases": 9805,
    "deaths": 234,
    "recovered": 8413,
    "new": 0,
    "newDeaths": 0
  },
  "Holy See": {
    "dateStr": "12/26/20",
    "cases": 27,
    "deaths": 0,
    "recovered": 15,
    "new": 0,
    "newDeaths": 0
  },
  "Honduras": {
    "dateStr": "12/26/20",
    "cases": 119097,
    "deaths": 3065,
    "recovered": 55704,
    "new": 438,
    "newDeaths": 4
  },
  "Hungary": {
    "dateStr": "12/26/20",
    "cases": 315362,
    "deaths": 8951,
    "recovered": 126482,
    "new": 1198,
    "newDeaths": 118
  },
  "Iceland": {
    "dateStr": "12/26/20",
    "cases": 5683,
    "deaths": 28,
    "recovered": 5506,
    "new": 0,
    "newDeaths": 0
  },
  "India": {
    "dateStr": "12/26/20",
    "cases": 10187850,
    "deaths": 147622,
    "recovered": 9761538,
    "new": 18732,
    "newDeaths": 279
  },
  "Indonesia": {
    "dateStr": "12/26/20",
    "cases": 706837,
    "deaths": 20994,
    "recovered": 576693,
    "new": 6740,
    "newDeaths": 147
  },
  "Iran": {
    "dateStr": "12/26/20",
    "cases": 1194963,
    "deaths": 54574,
    "recovered": 942548,
    "new": 5760,
    "newDeaths": 134
  },
  "Iraq": {
    "dateStr": "12/26/20",
    "cases": 590779,
    "deaths": 12767,
    "recovered": 530262,
    "new": 836,
    "newDeaths": 12
  },
  "Ireland": {
    "dateStr": "12/26/20",
    "cases": 85394,
    "deaths": 2200,
    "recovered": 23364,
    "new": 1296,
    "newDeaths": 6
  },
  "Israel": {
    "dateStr": "12/26/20",
    "cases": 398664,
    "deaths": 3210,
    "recovered": 359984,
    "new": 4273,
    "newDeaths": 24
  },
  "Italy": {
    "dateStr": "12/26/20",
    "cases": 2038759,
    "deaths": 71620,
    "recovered": 1386198,
    "new": 10405,
    "newDeaths": 261
  },
  "Jamaica": {
    "dateStr": "12/26/20",
    "cases": 12684,
    "deaths": 294,
    "recovered": 9881,
    "new": 87,
    "newDeaths": 0
  },
  "Japan": {
    "dateStr": "12/26/20",
    "cases": 218467,
    "deaths": 3062,
    "recovered": 180032,
    "new": 3892,
    "newDeaths": 46
  },
  "Jordan": {
    "dateStr": "12/26/20",
    "cases": 286356,
    "deaths": 3729,
    "recovered": 258651,
    "new": 1050,
    "newDeaths": 18
  },
  "Kazakhstan": {
    "dateStr": "12/26/20",
    "cases": 197142,
    "deaths": 2686,
    "recovered": 171798,
    "new": 926,
    "newDeaths": 1
  },
  "Kenya": {
    "dateStr": "12/26/20",
    "cases": 95843,
    "deaths": 1655,
    "recovered": 76998,
    "new": 130,
    "newDeaths": 2
  },
  "Korea, South": {
    "dateStr": "12/26/20",
    "cases": 56872,
    "deaths": 808,
    "recovered": 39040,
    "new": 970,
    "newDeaths": 15
  },
  "Kosovo": {
    "dateStr": "12/26/20",
    "cases": 50405,
    "deaths": 1305,
    "recovered": 39136,
    "new": 270,
    "newDeaths": 7
  },
  "Kuwait": {
    "dateStr": "12/26/20",
    "cases": 149449,
    "deaths": 929,
    "recovered": 145380,
    "new": 172,
    "newDeaths": 3
  },
  "Kyrgyzstan": {
    "dateStr": "12/26/20",
    "cases": 80182,
    "deaths": 1498,
    "recovered": 74477,
    "new": 157,
    "newDeaths": 0
  },
  "Laos": {
    "dateStr": "12/26/20",
    "cases": 41,
    "deaths": 0,
    "recovered": 37,
    "new": 0,
    "newDeaths": 0
  },
  "Latvia": {
    "dateStr": "12/26/20",
    "cases": 35819,
    "deaths": 515,
    "recovered": 24722,
    "new": 399,
    "newDeaths": 13
  },
  "Lebanon": {
    "dateStr": "12/26/20",
    "cases": 169472,
    "deaths": 1379,
    "recovered": 120780,
    "new": 1403,
    "newDeaths": 12
  },
  "Lesotho": {
    "dateStr": "12/26/20",
    "cases": 2725,
    "deaths": 51,
    "recovered": 1466,
    "new": 0,
    "newDeaths": 0
  },
  "Liberia": {
    "dateStr": "12/26/20",
    "cases": 1779,
    "deaths": 83,
    "recovered": 1406,
    "new": 0,
    "newDeaths": 0
  },
  "Libya": {
    "dateStr": "12/26/20",
    "cases": 97653,
    "deaths": 1415,
    "recovered": 68289,
    "new": 0,
    "newDeaths": 0
  },
  "Liechtenstein": {
    "dateStr": "12/26/20",
    "cases": 2000,
    "deaths": 31,
    "recovered": 1591,
    "new": 20,
    "newDeaths": 1
  },
  "Lithuania": {
    "dateStr": "12/26/20",
    "cases": 128931,
    "deaths": 1228,
    "recovered": 61345,
    "new": 2350,
    "newDeaths": 23
  },
  "Luxembourg": {
    "dateStr": "12/26/20",
    "cases": 45209,
    "deaths": 458,
    "recovered": 37574,
    "new": 0,
    "newDeaths": 0
  },
  "MS Zaandam": {
    "dateStr": "12/26/20",
    "cases": 9,
    "deaths": 2,
    "recovered": 7,
    "new": 0,
    "newDeaths": 0
  },
  "Madagascar": {
    "dateStr": "12/26/20",
    "cases": 17633,
    "deaths": 260,
    "recovered": 17147,
    "new": 0,
    "newDeaths": 0
  },
  "Malawi": {
    "dateStr": "12/26/20",
    "cases": 6343,
    "deaths": 188,
    "recovered": 5680,
    "new": 4,
    "newDeaths": 1
  },
  "Malaysia": {
    "dateStr": "12/26/20",
    "cases": 103900,
    "deaths": 451,
    "recovered": 83414,
    "new": 2335,
    "newDeaths": 2
  },
  "Maldives": {
    "dateStr": "12/26/20",
    "cases": 13618,
    "deaths": 48,
    "recovered": 13050,
    "new": 35,
    "newDeaths": 0
  },
  "Mali": {
    "dateStr": "12/26/20",
    "cases": 6574,
    "deaths": 249,
    "recovered": 4204,
    "new": 86,
    "newDeaths": 4
  },
  "Malta": {
    "dateStr": "12/26/20",
    "cases": 12241,
    "deaths": 206,
    "recovered": 10550,
    "new": 129,
    "newDeaths": 3
  },
  "Marshall Islands": {
    "dateStr": "12/26/20",
    "cases": 4,
    "deaths": 0,
    "recovered": 4,
    "new": 0,
    "newDeaths": 0
  },
  "Mauritania": {
    "dateStr": "12/26/20",
    "cases": 13516,
    "deaths": 321,
    "recovered": 10065,
    "new": 252,
    "newDeaths": 7
  },
  "Mauritius": {
    "dateStr": "12/26/20",
    "cases": 527,
    "deaths": 10,
    "recovered": 496,
    "new": 0,
    "newDeaths": 0
  },
  "Mexico": {
    "dateStr": "12/26/20",
    "cases": 1377217,
    "deaths": 122026,
    "recovered": 1031864,
    "new": 4974,
    "newDeaths": 189
  },
  "Moldova": {
    "dateStr": "12/26/20",
    "cases": 140996,
    "deaths": 2883,
    "recovered": 126651,
    "new": 746,
    "newDeaths": 12
  },
  "Monaco": {
    "dateStr": "12/26/20",
    "cases": 797,
    "deaths": 4,
    "recovered": 673,
    "new": 8,
    "newDeaths": 0
  },
  "Mongolia": {
    "dateStr": "12/26/20",
    "cases": 1121,
    "deaths": 0,
    "recovered": 711,
    "new": 39,
    "newDeaths": 0
  },
  "Montenegro": {
    "dateStr": "12/26/20",
    "cases": 46327,
    "deaths": 658,
    "recovered": 36373,
    "new": 382,
    "newDeaths": 6
  },
  "Morocco": {
    "dateStr": "12/26/20",
    "cases": 430562,
    "deaths": 7204,
    "recovered": 396095,
    "new": 2369,
    "newDeaths": 34
  },
  "Mozambique": {
    "dateStr": "12/26/20",
    "cases": 18162,
    "deaths": 159,
    "recovered": 16109,
    "new": 54,
    "newDeaths": 3
  },
  "Namibia": {
    "dateStr": "12/26/20",
    "cases": 21398,
    "deaths": 187,
    "recovered": 17851,
    "new": 136,
    "newDeaths": 0
  },
  "Nepal": {
    "dateStr": "12/26/20",
    "cases": 257700,
    "deaths": 1819,
    "recovered": 249132,
    "new": 500,
    "newDeaths": 3
  },
  "Netherlands": {
    "dateStr": "12/26/20",
    "cases": 753905,
    "deaths": 10970,
    "recovered": 0,
    "new": 9848,
    "newDeaths": 46
  },
  "New Zealand": {
    "dateStr": "12/26/20",
    "cases": 2144,
    "deaths": 25,
    "recovered": 2069,
    "new": 16,
    "newDeaths": 0
  },
  "Nicaragua": {
    "dateStr": "12/26/20",
    "cases": 5991,
    "deaths": 164,
    "recovered": 4225,
    "new": 0,
    "newDeaths": 0
  },
  "Niger": {
    "dateStr": "12/26/20",
    "cases": 3057,
    "deaths": 94,
    "recovered": 1673,
    "new": 52,
    "newDeaths": 3
  },
  "Nigeria": {
    "dateStr": "12/26/20",
    "cases": 83576,
    "deaths": 1247,
    "recovered": 70495,
    "new": 829,
    "newDeaths": 1
  },
  "North Macedonia": {
    "dateStr": "12/26/20",
    "cases": 81425,
    "deaths": 2427,
    "recovered": 58720,
    "new": 529,
    "newDeaths": 26
  },
  "Norway": {
    "dateStr": "12/26/20",
    "cases": 46678,
    "deaths": 421,
    "recovered": 17998,
    "new": 430,
    "newDeaths": 0
  },
  "Oman": {
    "dateStr": "12/26/20",
    "cases": 128290,
    "deaths": 1491,
    "recovered": 120441,
    "new": 0,
    "newDeaths": 0
  },
  "Pakistan": {
    "dateStr": "12/26/20",
    "cases": 471335,
    "deaths": 9874,
    "recovered": 422132,
    "new": 1853,
    "newDeaths": 58
  },
  "Panama": {
    "dateStr": "12/26/20",
    "cases": 228724,
    "deaths": 3799,
    "recovered": 183522,
    "new": 2064,
    "newDeaths": 43
  },
  "Papua New Guinea": {
    "dateStr": "12/26/20",
    "cases": 780,
    "deaths": 9,
    "recovered": 661,
    "new": 0,
    "newDeaths": 0
  },
  "Paraguay": {
    "dateStr": "12/26/20",
    "cases": 104162,
    "deaths": 2174,
    "recovered": 77359,
    "new": 274,
    "newDeaths": 20
  },
  "Peru": {
    "dateStr": "12/26/20",
    "cases": 1005546,
    "deaths": 37368,
    "recovered": 941668,
    "new": 1564,
    "newDeaths": 51
  },
  "Philippines": {
    "dateStr": "12/26/20",
    "cases": 469005,
    "deaths": 9067,
    "recovered": 431055,
    "new": 1404,
    "newDeaths": 5
  },
  "Poland": {
    "dateStr": "12/26/20",
    "cases": 1253957,
    "deaths": 27061,
    "recovered": 992381,
    "new": 4878,
    "newDeaths": 69
  },
  "Portugal": {
    "dateStr": "12/26/20",
    "cases": 392996,
    "deaths": 6556,
    "recovered": 316671,
    "new": 1214,
    "newDeaths": 78
  },
  "Qatar": {
    "dateStr": "12/26/20",
    "cases": 142903,
    "deaths": 244,
    "recovered": 140687,
    "new": 169,
    "newDeaths": 0
  },
  "Romania": {
    "dateStr": "12/26/20",
    "cases": 613760,
    "deaths": 15108,
    "recovered": 536332,
    "new": 1387,
    "newDeaths": 85
  },
  "Russia": {
    "dateStr": "12/26/20",
    "cases": 2992123,
    "deaths": 53539,
    "recovered": 2402122,
    "new": 28833,
    "newDeaths": 554
  },
  "Rwanda": {
    "dateStr": "12/26/20",
    "cases": 7817,
    "deaths": 72,
    "recovered": 6227,
    "new": 74,
    "newDeaths": 3
  },
  "Saint Kitts and Nevis": {
    "dateStr": "12/26/20",
    "cases": 30,
    "deaths": 0,
    "recovered": 26,
    "new": 0,
    "newDeaths": 0
  },
  "Saint Lucia": {
    "dateStr": "12/26/20",
    "cases": 305,
    "deaths": 5,
    "recovered": 267,
    "new": 0,
    "newDeaths": 0
  },
  "Saint Vincent and the Grenadines": {
    "dateStr": "12/26/20",
    "cases": 109,
    "deaths": 0,
    "recovered": 87,
    "new": 1,
    "newDeaths": 0
  },
  "Samoa": {
    "dateStr": "12/26/20",
    "cases": 2,
    "deaths": 0,
    "recovered": 2,
    "new": 0,
    "newDeaths": 0
  },
  "San Marino": {
    "dateStr": "12/26/20",
    "cases": 2231,
    "deaths": 56,
    "recovered": 1863,
    "new": 0,
    "newDeaths": 0
  },
  "Sao Tome and Principe": {
    "dateStr": "12/26/20",
    "cases": 1014,
    "deaths": 17,
    "recovered": 963,
    "new": 0,
    "newDeaths": 0
  },
  "Saudi Arabia": {
    "dateStr": "12/26/20",
    "cases": 362066,
    "deaths": 6176,
    "recovered": 353004,
    "new": 163,
    "newDeaths": 8
  },
  "Senegal": {
    "dateStr": "12/26/20",
    "cases": 18523,
    "deaths": 387,
    "recovered": 16881,
    "new": 154,
    "newDeaths": 1
  },
  "Serbia": {
    "dateStr": "12/26/20",
    "cases": 323367,
    "deaths": 2983,
    "recovered": 15564,
    "new": 3200,
    "newDeaths": 52
  },
  "Seychelles": {
    "dateStr": "12/26/20",
    "cases": 205,
    "deaths": 0,
    "recovered": 184,
    "new": 0,
    "newDeaths": 0
  },
  "Sierra Leone": {
    "dateStr": "12/26/20",
    "cases": 2549,
    "deaths": 76,
    "recovered": 1870,
    "new": 0,
    "newDeaths": 0
  },
  "Singapore": {
    "dateStr": "12/26/20",
    "cases": 58519,
    "deaths": 29,
    "recovered": 58362,
    "new": 10,
    "newDeaths": 0
  },
  "Slovakia": {
    "dateStr": "12/26/20",
    "cases": 166649,
    "deaths": 1732,
    "recovered": 116948,
    "new": 1041,
    "newDeaths": 0
  },
  "Slovenia": {
    "dateStr": "12/26/20",
    "cases": 114184,
    "deaths": 2532,
    "recovered": 92986,
    "new": 369,
    "newDeaths": 25
  },
  "Solomon Islands": {
    "dateStr": "12/26/20",
    "cases": 17,
    "deaths": 0,
    "recovered": 5,
    "new": 0,
    "newDeaths": 0
  },
  "Somalia": {
    "dateStr": "12/26/20",
    "cases": 4690,
    "deaths": 127,
    "recovered": 3605,
    "new": 0,
    "newDeaths": 0
  },
  "South Africa": {
    "dateStr": "12/26/20",
    "cases": 994911,
    "deaths": 26521,
    "recovered": 839194,
    "new": 11552,
    "newDeaths": 245
  },
  "South Sudan": {
    "dateStr": "12/26/20",
    "cases": 3455,
    "deaths": 62,
    "recovered": 3118,
    "new": 0,
    "newDeaths": 0
  },
  "Spain": {
    "dateStr": "12/26/20",
    "cases": 1854951,
    "deaths": 49824,
    "recovered": 150376,
    "new": 0,
    "newDeaths": 0
  },
  "Sri Lanka": {
    "dateStr": "12/26/20",
    "cases": 40380,
    "deaths": 187,
    "recovered": 32051,
    "new": 598,
    "newDeaths": 1
  },
  "Sudan": {
    "dateStr": "12/26/20",
    "cases": 23316,
    "deaths": 1468,
    "recovered": 13524,
    "new": 0,
    "newDeaths": 0
  },
  "Suriname": {
    "dateStr": "12/26/20",
    "cases": 5938,
    "deaths": 119,
    "recovered": 5456,
    "new": 58,
    "newDeaths": 0
  },
  "Sweden": {
    "dateStr": "12/26/20",
    "cases": 396048,
    "deaths": 8279,
    "recovered": 0,
    "new": 0,
    "newDeaths": 0
  },
  "Switzerland": {
    "dateStr": "12/26/20",
    "cases": 428197,
    "deaths": 7193,
    "recovered": 311500,
    "new": 0,
    "newDeaths": 34
  },
  "Syria": {
    "dateStr": "12/26/20",
    "cases": 10932,
    "deaths": 669,
    "recovered": 5093,
    "new": 111,
    "newDeaths": 9
  },
  "Taiwan*": {
    "dateStr": "12/26/20",
    "cases": 783,
    "deaths": 7,
    "recovered": 647,
    "new": 3,
    "newDeaths": 0
  },
  "Tajikistan": {
    "dateStr": "12/26/20",
    "cases": 13172,
    "deaths": 90,
    "recovered": 12657,
    "new": 34,
    "newDeaths": 1
  },
  "Tanzania": {
    "dateStr": "12/26/20",
    "cases": 509,
    "deaths": 21,
    "recovered": 183,
    "new": 0,
    "newDeaths": 0
  },
  "Thailand": {
    "dateStr": "12/26/20",
    "cases": 6123,
    "deaths": 60,
    "recovered": 4161,
    "new": 103,
    "newDeaths": 0
  },
  "Timor-Leste": {
    "dateStr": "12/26/20",
    "cases": 41,
    "deaths": 0,
    "recovered": 35,
    "new": 0,
    "newDeaths": 0
  },
  "Togo": {
    "dateStr": "12/26/20",
    "cases": 3555,
    "deaths": 68,
    "recovered": 3261,
    "new": 9,
    "newDeaths": 0
  },
  "Trinidad and Tobago": {
    "dateStr": "12/26/20",
    "cases": 7104,
    "deaths": 125,
    "recovered": 6545,
    "new": 7,
    "newDeaths": 0
  },
  "Tunisia": {
    "dateStr": "12/26/20",
    "cases": 130230,
    "deaths": 4426,
    "recovered": 99514,
    "new": 1652,
    "newDeaths": 41
  },
  "Turkey": {
    "dateStr": "12/26/20",
    "cases": 2133373,
    "deaths": 19624,
    "recovered": 1994034,
    "new": 15118,
    "newDeaths": 253
  },
  "US": {
    "dateStr": "12/26/20",
    "cases": 18982634,
    "deaths": 331909,
    "recovered": 6298082,
    "new": 226274,
    "newDeaths": 1663
  },
  "Uganda": {
    "dateStr": "12/26/20",
    "cases": 33563,
    "deaths": 245,
    "recovered": 11055,
    "new": 203,
    "newDeaths": 0
  },
  "Ukraine": {
    "dateStr": "12/26/20",
    "cases": 1049717,
    "deaths": 18389,
    "recovered": 676234,
    "new": 8134,
    "newDeaths": 134
  },
  "United Arab Emirates": {
    "dateStr": "12/26/20",
    "cases": 200892,
    "deaths": 655,
    "recovered": 177407,
    "new": 1227,
    "newDeaths": 2
  },
  "United Kingdom": {
    "dateStr": "12/26/20",
    "cases": 2256005,
    "deaths": 70405,
    "recovered": 344,
    "new": 34693,
    "newDeaths": 210
  },
  "Uruguay": {
    "dateStr": "12/26/20",
    "cases": 16218,
    "deaths": 147,
    "recovered": 10847,
    "new": 370,
    "newDeaths": 4
  },
  "Uzbekistan": {
    "dateStr": "12/26/20",
    "cases": 76666,
    "deaths": 612,
    "recovered": 74291,
    "new": 98,
    "newDeaths": 0
  },
  "Vanuatu": {
    "dateStr": "12/26/20",
    "cases": 1,
    "deaths": 0,
    "recovered": 1,
    "new": 0,
    "newDeaths": 0
  },
  "Venezuela": {
    "dateStr": "12/26/20",
    "cases": 111951,
    "deaths": 1013,
    "recovered": 106105,
    "new": 348,
    "newDeaths": 3
  },
  "Vietnam": {
    "dateStr": "12/26/20",
    "cases": 1440,
    "deaths": 35,
    "recovered": 1303,
    "new": 1,
    "newDeaths": 0
  },
  "West Bank and Gaza": {
    "dateStr": "12/26/20",
    "cases": 131904,
    "deaths": 1281,
    "recovered": 108118,
    "new": 1306,
    "newDeaths": 21
  },
  "Yemen": {
    "dateStr": "12/26/20",
    "cases": 2383,
    "deaths": 649,
    "recovered": 1554,
    "new": 0,
    "newDeaths": 0
  },
  "Zambia": {
    "dateStr": "12/26/20",
    "cases": 19671,
    "deaths": 382,
    "recovered": 18200,
    "new": 100,
    "newDeaths": 1
  },
  "Zimbabwe": {
    "dateStr": "12/26/20",
    "cases": 12963,
    "deaths": 341,
    "recovered": 10519,
    "new": 83,
    "newDeaths": 0
  },
  "Canada": {
    "dateStr": "12/26/20",
    "cases": 540941,
    "deaths": 14769,
    "recovered": 0,
    "new": 2200,
    "newDeaths": 23
  },
  "Australia": {
    "dateStr": "12/26/20",
    "cases": 28308,
    "deaths": 908,
    "recovered": 25730,
    "new": 11,
    "newDeaths": 0
  },
  "China": {
    "dateStr": "12/26/20",
    "cases": 95541,
    "deaths": 4770,
    "recovered": 89423,
    "new": 81,
    "newDeaths": 0
  },
  "World": {
    "dateStr": "12/26/20",
    "cases": 80273969,
    "deaths": 1756972,
    "recovered": 46899934,
    "new": 511209,
    "newDeaths": 7075
  }
}